tello_dron_simple_flight-0.1.2.dist-info/METADATA
tello_dron_simple_flight-0.1.2.dist-info/WHEEL
tello_dron_simple_flight/__init__.py
tello_dron_simple_flight-0.1.2.dist-info/RECORD
