Metadata-Version: 2.1
Name: tello-dron-simple-flight
Version: 0.1.2
Summary: Take-off and landing and forward and reverse or right turn - end
Author-Email: pysatellite <pysatellite@gmail.com>
License: GNU
Requires-Python: >=3.11
